Metadata-Version: 1.1
Name: pwm-tool
Version: 0.3.1
Summary: password manager tool
Home-page: https://github.com/ls0f/pwm
Author: lovedboy
Author-email: lovedboy.tk@qq.com
License: BSD
Platform: UNKNOWN
Classifier: License :: OSI Approved :: MIT License
Classifier: Programming Language :: Python
Classifier: Intended Audience :: Developers
Classifier: Operating System :: OS Independent
